{
  "name": "server",
  "dependencies": {
    "axios": {
      "version": "1.4.0",
      "resolved": "https://registry.npmjs.org/axios/-/axios-1.4.0.tgz",
      "overridden": false
    },
    "cors": {
      "version": "2.8.5",
      "resolved": "https://registry.npmjs.org/cors/-/cors-2.8.5.tgz",
      "overridden": false
    },
    "express": {
      "version": "4.18.2",
      "resolved": "https://registry.npmjs.org/express/-/express-4.18.2.tgz",
      "overridden": false
    },
    "mysql": {
      "version": "2.18.1",
      "resolved": "https://registry.npmjs.org/mysql/-/mysql-2.18.1.tgz",
      "overridden": false
    },
    "redis": {
      "version": "4.6.6",
      "resolved": "https://registry.npmjs.org/redis/-/redis-4.6.6.tgz",
      "overridden": false
    }
  }
}
